semanticscholar_datasetapi/__init__.py
semanticscholar_datasetapi/api.py
semanticscholar_datasetapi-0.1.2.dist-info/LICENSE
semanticscholar_datasetapi-0.1.2.dist-info/METADATA
semanticscholar_datasetapi-0.1.2.dist-info/WHEEL
semanticscholar_datasetapi-0.1.2.dist-info/top_level.txt
semanticscholar_datasetapi-0.1.2.dist-info/RECORD
