Metadata-Version: 2.2
Name: semanticscholar_datasetapi
Version: 0.1.2
Summary: A Python wrapper for the Semantic Scholar Dataset API that provides easy access to academic papers, citations, and related data
Home-page: https://github.com/k1000dai/semanticscholar-datasetapi
Author: Kohei Sendai
Author-email: your.email@example.com
Project-URL: Bug Tracker, https://github.com/k1000dai/semanticscholar-datasetapi/issues
Project-URL: Documentation, https://github.com/k1000dai/semanticscholar-datasetapi#readme
Project-URL: Source Code, https://github.com/k1000dai/semanticscholar-datasetapi
Keywords: semantic scholar,dataset,academic papers,citations,research,api
Classifier: Development Status :: 4 - Beta
Classifier: Intended Audience :: Science/Research
Classifier: Intended Audience :: Developers
Classifier: License :: OSI Approved :: MIT License
Classifier: Operating System :: OS Independent
Classifier: Programming Language :: Python :: 3
Classifier: Programming Language :: Python :: 3.7
Classifier: Programming Language :: Python :: 3.8
Classifier: Programming Language :: Python :: 3.9
Classifier: Programming Language :: Python :: 3.10
Classifier: Programming Language :: Python :: 3.11
Classifier: Topic :: Scientific/Engineering
Classifier: Topic :: Software Development :: Libraries :: Python Modules
Classifier: Typing :: Typed
Requires-Python: >=3.7
License-File: LICENSE
Requires-Dist: requests>=2.25.0
Requires-Dist: typing; python_version < "3.8"
Dynamic: author
Dynamic: author-email
Dynamic: classifier
Dynamic: description
Dynamic: description-content-type
Dynamic: home-page
Dynamic: keywords
Dynamic: project-url
Dynamic: requires-dist
Dynamic: requires-python
Dynamic: summary
